neutrolab/__init__.py
neutrolab/aggregation.py
neutrolab/fsqca.py
neutrolab/py.typed
neutrolab/stance.py
neutrolab/tsetlin.py
neutrolab/utils.py
neutrolab/methods/__init__.py
neutrolab/methods/base.py
neutrolab/methods/fuzzy.py
neutrolab/methods/kde.py
neutrolab/methods/kmeans.py
neutrolab/methods/parabolic.py
neutrolab/methods/threshold.py
neutrolab-1.4.0.dist-info/licenses/LICENSE
neutrolab-1.4.0.dist-info/METADATA
neutrolab-1.4.0.dist-info/WHEEL
neutrolab-1.4.0.dist-info/top_level.txt
neutrolab-1.4.0.dist-info/RECORD
