Metadata-Version: 2.4
Name: neutrolab
Version: 1.4.0
Summary: NeutroLab: A Unified Library for Neutrosophic Learning, Configuration Analysis, and Decision-Making under Uncertainty
Author-email: Maikel Yelandi Leyva-Vázquez <mleyvaz@gmail.com>, Florentin Smarandache <smarand@unm.edu>
Maintainer-email: Maikel Yelandi Leyva-Vázquez <mleyvaz@gmail.com>
License: MIT
Project-URL: Homepage, https://github.com/maikelleyva/neutrolab
Project-URL: Documentation, https://neutrolab.readthedocs.io
Project-URL: Repository, https://github.com/maikelleyva/neutrolab
Project-URL: Issues, https://github.com/maikelleyva/neutrolab/issues
Project-URL: Changelog, https://github.com/maikelleyva/neutrolab/blob/main/CHANGELOG.md
Project-URL: Paper, https://doi.org/10.xxxxx/neutrosophication
Keywords: neutrosophic,neutrosophication,neutrosophic sets,fuzzy logic,uncertainty quantification,indeterminacy,machine learning,data science,medical informatics,clustering,membership functions,decision making,SVNS,truth-indeterminacy-falsity
Classifier: Development Status :: 4 - Beta
Classifier: Intended Audience :: Developers
Classifier: Intended Audience :: Science/Research
Classifier: Intended Audience :: Healthcare Industry
Classifier: License :: OSI Approved :: MIT License
Classifier: Operating System :: OS Independent
Classifier: Programming Language :: Python :: 3
Classifier: Programming Language :: Python :: 3.8
Classifier: Programming Language :: Python :: 3.9
Classifier: Programming Language :: Python :: 3.10
Classifier: Programming Language :: Python :: 3.11
Classifier: Programming Language :: Python :: 3.12
Classifier: Topic :: Scientific/Engineering
Classifier: Topic :: Scientific/Engineering :: Artificial Intelligence
Classifier: Topic :: Scientific/Engineering :: Mathematics
Classifier: Topic :: Scientific/Engineering :: Medical Science Apps.
Classifier: Topic :: Scientific/Engineering :: Information Analysis
Requires-Python: >=3.8
License-File: LICENSE
Requires-Dist: numpy>=1.20.0
Requires-Dist: pandas>=1.3.0
Requires-Dist: scipy>=1.7.0
Provides-Extra: dev
Requires-Dist: pytest>=7.0.0; extra == "dev"
Requires-Dist: pytest-cov>=4.0.0; extra == "dev"
Requires-Dist: black>=23.0.0; extra == "dev"
Requires-Dist: isort>=5.12.0; extra == "dev"
Requires-Dist: mypy>=1.0.0; extra == "dev"
Requires-Dist: flake8>=6.0.0; extra == "dev"
Provides-Extra: docs
Requires-Dist: sphinx>=6.0.0; extra == "docs"
Requires-Dist: sphinx-rtd-theme>=1.2.0; extra == "docs"
Requires-Dist: myst-parser>=1.0.0; extra == "docs"
Provides-Extra: viz
Requires-Dist: matplotlib>=3.5.0; extra == "viz"
Requires-Dist: seaborn>=0.12.0; extra == "viz"
Provides-Extra: all
Requires-Dist: neutrolab[dev,docs,viz]; extra == "all"
Dynamic: license-file
